factorysimpy/__init__.py
factorysimpy/base/__init__.py
factorysimpy/base/belt_store.py
factorysimpy/base/buffer_store.py
factorysimpy/base/fleet_store.py
factorysimpy/base/priority_req_store.py
factorysimpy/base/reservable_priority_req_filter_store.py
factorysimpy/base/reservable_priority_req_store.py
factorysimpy/base/slotted_belt_store.py
factorysimpy/constructs/__init__.py
factorysimpy/constructs/chain.py
factorysimpy/constructs/mesh.py
factorysimpy/edges/__init__.py
factorysimpy/edges/buffer.py
factorysimpy/edges/continuous_conveyor.py
factorysimpy/edges/edge.py
factorysimpy/edges/fleet.py
factorysimpy/edges/slotted_conveyor.py
factorysimpy/helper/__init__.py
factorysimpy/helper/baseflowitem.py
factorysimpy/helper/item.py
factorysimpy/helper/pallet.py
factorysimpy/nodes/__init__.py
factorysimpy/nodes/combiner.py
factorysimpy/nodes/machine.py
factorysimpy/nodes/node.py
factorysimpy/nodes/sink.py
factorysimpy/nodes/source.py
factorysimpy/nodes/splitter.py
factorysimpy/utils/__init__.py
factorysimpy/utils/stats_summary.py
factorysimpy/utils/utils.py
factorysimpy-0.1.0b3.dist-info/licenses/LICENSE
factorysimpy-0.1.0b3.dist-info/METADATA
factorysimpy-0.1.0b3.dist-info/WHEEL
factorysimpy-0.1.0b3.dist-info/top_level.txt
factorysimpy-0.1.0b3.dist-info/RECORD
