Metadata-Version: 2.4
Name: factorysimpy
Version: 0.1.0b3
Summary: A light-weight component library for simulating manufacturing systems, based on SimPy
Author-email: Lekshmi P <lekshmi20231101@iitgoa.ac.in>, Neha Karanjkar <nehak@iitgoa.ac.in>
License: MIT
Project-URL: Homepage, https://factorysimpy.github.io/FactorySimPy/
Project-URL: Repository, https://github.com/FactorySimPy/FactorySimPy
Requires-Python: >=3.8
License-File: LICENSE
Requires-Dist: simpy>=4.1.1
Provides-Extra: dev
Requires-Dist: pytest>=7.0; extra == "dev"
Requires-Dist: pytest-asyncio; extra == "dev"
Dynamic: license-file
